README.md
setup.cfg
setup.py
dist_romakot/__init__.py
dist_romakot/lib.py
lib_test_yan.egg-info/PKG-INFO
lib_test_yan.egg-info/SOURCES.txt
lib_test_yan.egg-info/dependency_links.txt
lib_test_yan.egg-info/not-zip-safe
lib_test_yan.egg-info/top_level.txt