Metadata-Version: 1.0
Name: lib-test-yan
Version: 0.1
Summary: First lib
Home-page: UNKNOWN
Author: romakot
Author-email: dota234con@mail.ru
License: UNKNOWN
Platform: UNKNOWN
